{
  // ACTION REQUIRED: This file was automatically added to your project, but it
  // will not take effect until additional steps are taken to enable it. See the
  // following page for additional information:
  //
  // https://github.com/DotNetAnalyzers/StyleCopAnalyzers/blob/master/documentation/EnableConfiguration.md

  "$schema": "https://raw.githubusercontent.com/DotNetAnalyzers/StyleCopAnalyzers/master/StyleCop.Analyzers/StyleCop.Analyzers/Settings/stylecop.schema.json",
  "settings": {
    "documentationRules": {
      "xmlHeader": false,
      "companyName": "Stratiteq Sweden AB",
      "copyrightText": "Copyright (c) {companyName}. All rights reserved.\n\nLicensed under the {licenseName} license. See {licenseFile} file in the project root for full license information.",
      "variables": {
        "licenseName": "MIT",
        "licenseFile": "LICENSE"
      },
      "documentInterfaces": false,
      "documentExposedElements": false,
      "documentInternalElements": false,
      "documentPrivateElements": false,
      "documentPrivateFields": false
    },
    "orderingRules": {
      "usingDirectivesPlacement": "outsideNamespace",
      "elementOrder": [ "kind", "accessibility", "constant", "static", "readonly" ]
    },
    "maintainabilityRules": {
      "topLevelTypes": [ "class", "interface", "struct" ]
    }
  }
}
